{"features":[{"stringID":null,"fieldNames":["SMID","SMUSERID","SMGEOMETRY","OBJ_ID","MNTN_ID","MNTN_NM","MNTN_HGHT","PHTGR_NO","EMNDN_CD","EMNDN_NM"],"geometry":{"center":{"x":129.01250273998295,"y":37.308715479727695},"parts":[1],"style":null,"prjCoordSys":null,"id":1,"type":"POINT","partTopo":null,"points":[{"x":129.01250273998295,"y":37.308715479727695}]},"fieldValues":["1","0","[B@87cb026","3","25","덕항산","1071.0","0.0","51190116","하사미동"],"ID":1},{"stringID":null,"fieldNames":["SMID","SMUSERID","SMGEOMETRY","OBJ_ID","MNTN_ID","MNTN_NM","MNTN_HGHT","PHTGR_NO","EMNDN_CD","EMNDN_NM"],"geometry":{"center":{"x":128.91608680271824,"y":37.09844845436117},"parts":[1],"style":null,"prjCoordSys":null,"id":2,"type":"POINT","partTopo":null,"points":[{"x":128.91608680271824,"y":37.09844845436117}]},"fieldValues":["2","0","[B@523fa58b","4","88","태백산","1567.0","0.0","51190108","혈동"],"ID":2},{"stringID":null,"fieldNames":["SMID","SMUSERID","SMGEOMETRY","OBJ_ID","MNTN_ID","MNTN_NM","MNTN_HGHT","PHTGR_NO","EMNDN_CD","EMNDN_NM"],"geometry":{"center":{"x":128.2936237772579,"y":37.396539583885406},"parts":[1],"style":null,"prjCoordSys":null,"id":3,"type":"POINT","partTopo":null,"points":[{"x":128.2936237772579,"y":37.396539583885406}]},"fieldValues":["3","0","[B@5762715d","5","41","백덕산","1350.0","0.0","51750370","수주면"],"ID":3},{"stringID":null,"fieldNames":["SMID","SMUSERID","SMGEOMETRY","OBJ_ID","MNTN_ID","MNTN_NM","MNTN_HGHT","PHTGR_NO","EMNDN_CD","EMNDN_NM"],"geometry":{"center":{"x":128.48520141129416,"y":37.117477911856},"parts":[1],"style":null,"prjCoordSys":null,"id":4,"type":"POINT","partTopo":null,"points":[{"x":128.48520141129416,"y":37.117477911856}]},"fieldValues":["4","0","[B@695d3c6a","6","89","태화산","1027.0","0.0","51750250","영월읍"],"ID":4},{"stringID":null,"fieldNames":["SMID","SMUSERID","SMGEOMETRY","OBJ_ID","MNTN_ID","MNTN_NM","MNTN_HGHT","PHTGR_NO","EMNDN_CD","EMNDN_NM"],"geometry":{"center":{"x":128.5635737334791,"y":37.46188651110358},"parts":[1],"style":null,"prjCoordSys":null,"id":5,"type":"POINT","partTopo":null,"points":[{"x":128.5635737334791,"y":37.46188651110358}]},"fieldValues":["5","0","[B@44d5ce7","7","3","가리왕산","1561.0","0.0","51760360","진부면"],"ID":5},{"stringID":null,"fieldNames":["SMID","SMUSERID","SMGEOMETRY","OBJ_ID","MNTN_ID","MNTN_NM","MNTN_HGHT","PHTGR_NO","EMNDN_CD","EMNDN_NM"],"geometry":{"center":{"x":128.5961446587304,"y":37.28010180713352},"parts":[1],"style":null,"prjCoordSys":null,"id":6,"type":"POINT","partTopo":null,"points":[{"x":128.5961446587304,"y":37.28010180713352}]},"fieldValues":["6","0","[B@2bf1b218","8","45","백운산(정선)","883.0","0.0","51760310","미탄면"],"ID":6},{"stringID":null,"fieldNames":["SMID","SMUSERID","SMGEOMETRY","OBJ_ID","MNTN_ID","MNTN_NM","MNTN_HGHT","PHTGR_NO","EMNDN_CD","EMNDN_NM"],"geometry":{"center":{"x":128.4254173595368,"y":38.048737562755804},"parts":[1],"style":null,"prjCoordSys":null,"id":7,"type":"POINT","partTopo":null,"points":[{"x":128.4254173595368,"y":38.048737562755804}]},"fieldValues":["7","0","[B@6fddd6a2","9","73","점봉산","1424.0","0.0","51810250","인제읍"],"ID":7},{"stringID":null,"fieldNames":["SMID","SMUSERID","SMGEOMETRY","OBJ_ID","MNTN_ID","MNTN_NM","MNTN_HGHT","PHTGR_NO","EMNDN_CD","EMNDN_NM"],"geometry":{"center":{"x":127.95635142530367,"y":37.87108173416483},"parts":[1],"style":null,"prjCoordSys":null,"id":8,"type":"POINT","partTopo":null,"points":[{"x":127.95635142530367,"y":37.87108173416483}]},"fieldValues":["8","0","[B@6f63095f","12","2","가리산","1051.0","0.0","51110380","북산면"],"ID":8},{"stringID":null,"fieldNames":["SMID","SMUSERID","SMGEOMETRY","OBJ_ID","MNTN_ID","MNTN_NM","MNTN_HGHT","PHTGR_NO","EMNDN_CD","EMNDN_NM"],"geometry":{"center":{"x":127.66052551832544,"y":37.83980833218117},"parts":[1],"style":null,"prjCoordSys":null,"id":9,"type":"POINT","partTopo":null,"points":[{"x":127.66052551832544,"y":37.83980833218117}]},"fieldValues":["9","0","[B@1a7ca30","13","49","삼악산","654.0","0.0","51110350","서면"],"ID":9},{"stringID":null,"fieldNames":["SMID","SMUSERID","SMGEOMETRY","OBJ_ID","MNTN_ID","MNTN_NM","MNTN_HGHT","PHTGR_NO","EMNDN_CD","EMNDN_NM"],"geometry":{"center":{"x":128.0100511644471,"y":37.71524521805631},"parts":[1],"style":null,"prjCoordSys":null,"id":10,"type":"POINT","partTopo":null,"points":[{"x":128.0100511644471,"y":37.71524521805631}]},"fieldValues":["10","0","[B@27e0d96e","14","9","공작산","887.0","0.0","51110390","동내면"],"ID":10},{"stringID":null,"fieldNames":["SMID","SMUSERID","SMGEOMETRY","OBJ_ID","MNTN_ID","MNTN_NM","MNTN_HGHT","PHTGR_NO","EMNDN_CD","EMNDN_NM"],"geometry":{"center":{"x":128.05541649631033,"y":37.365104700206466},"parts":[1],"style":null,"prjCoordSys":null,"id":11,"type":"POINT","partTopo":null,"points":[{"x":128.05541649631033,"y":37.365104700206466}]},"fieldValues":["11","0","[B@260973f6","15","86","치악산","1288.0","0.0","51130310","소초면"],"ID":11},{"stringID":null,"fieldNames":["SMID","SMUSERID","SMGEOMETRY","OBJ_ID","MNTN_ID","MNTN_NM","MNTN_HGHT","PHTGR_NO","EMNDN_CD","EMNDN_NM"],"geometry":{"center":{"x":128.46591131956947,"y":37.728321024796635},"parts":[1],"style":null,"prjCoordSys":null,"id":12,"type":"POINT","partTopo":null,"points":[{"x":128.46591131956947,"y":37.728321024796635}]},"fieldValues":["12","0","[B@5157bf99","16","8","계방산","1577.0","0.0","51720390","내면"],"ID":12},{"stringID":null,"fieldNames":["SMID","SMUSERID","SMGEOMETRY","OBJ_ID","MNTN_ID","MNTN_NM","MNTN_HGHT","PHTGR_NO","EMNDN_CD","EMNDN_NM"],"geometry":{"center":{"x":128.54305009750772,"y":37.794123882926975},"parts":[1],"style":null,"prjCoordSys":null,"id":13,"type":"POINT","partTopo":null,"points":[{"x":128.54305009750772,"y":37.794123882926975}]},"fieldValues":["13","0","[B@6e9e19c9","17","59","오대산","1563.0","0.0","51720390","내면"],"ID":13},{"stringID":null,"fieldNames":["SMID","SMUSERID","SMGEOMETRY","OBJ_ID","MNTN_ID","MNTN_NM","MNTN_HGHT","PHTGR_NO","EMNDN_CD","EMNDN_NM"],"geometry":{"center":{"x":127.33800199362103,"y":38.10428164071305},"parts":[1],"style":null,"prjCoordSys":null,"id":14,"type":"POINT","partTopo":null,"points":[{"x":127.33800199362103,"y":38.10428164071305}]},"fieldValues":["14","0","[B@4f9486dd","19","32","명성산","923.0","0.0","51780256","갈말읍"],"ID":14},{"stringID":null,"fieldNames":["SMID","SMUSERID","SMGEOMETRY","OBJ_ID","MNTN_ID","MNTN_NM","MNTN_HGHT","PHTGR_NO","EMNDN_CD","EMNDN_NM"],"geometry":{"center":{"x":127.80407346087847,"y":38.000576830099},"parts":[1],"style":null,"prjCoordSys":null,"id":15,"type":"POINT","partTopo":null,"points":[{"x":127.80407346087847,"y":38.000576830099}]},"fieldValues":["15","0","[B@22efca1a","21","60","오봉산","779.0","0.0","51790310","간동면"],"ID":15},{"stringID":null,"fieldNames":["SMID","SMUSERID","SMGEOMETRY","OBJ_ID","MNTN_ID","MNTN_NM","MNTN_HGHT","PHTGR_NO","EMNDN_CD","EMNDN_NM"],"geometry":{"center":{"x":128.1347564636627,"y":38.21098325239825},"parts":[1],"style":null,"prjCoordSys":null,"id":16,"type":"POINT","partTopo":null,"points":[{"x":128.1347564636627,"y":38.21098325239825}]},"fieldValues":["16","0","[B@4e2812a9","22","21","대암산","1304.0","0.0","51800340","해안면"],"ID":16},{"stringID":null,"fieldNames":["SMID","SMUSERID","SMGEOMETRY","OBJ_ID","MNTN_ID","MNTN_NM","MNTN_HGHT","PHTGR_NO","EMNDN_CD","EMNDN_NM"],"geometry":{"center":{"x":127.08703880257595,"y":37.93718096658094},"parts":[1],"style":null,"prjCoordSys":null,"id":17,"type":"POINT","partTopo":null,"points":[{"x":127.08703880257595,"y":37.93718096658094}]},"fieldValues":["17","0","[B@50661af4","23","55","소요산","587.0","0.0","41250110","하봉암동"],"ID":17},{"stringID":null,"fieldNames":["SMID","SMUSERID","SMGEOMETRY","OBJ_ID","MNTN_ID","MNTN_NM","MNTN_HGHT","PHTGR_NO","EMNDN_CD","EMNDN_NM"],"geometry":{"center":{"x":126.9779895597336,"y":37.65865196290704},"parts":[1],"style":null,"prjCoordSys":null,"id":18,"type":"POINT","partTopo":null,"points":[{"x":126.9779895597336,"y":37.65865196290704}]},"fieldValues":["18","0","[B@3bafdc4b","24","47","북한산","837.0","0.0","41281107","북한동"],"ID":18},{"stringID":null,"fieldNames":["SMID","SMUSERID","SMGEOMETRY","OBJ_ID","MNTN_ID","MNTN_NM","MNTN_HGHT","PHTGR_NO","EMNDN_CD","EMNDN_NM"],"geometry":{"center":{"x":127.27266540725905,"y":37.679977265553894},"parts":[1],"style":null,"prjCoordSys":null,"id":19,"type":"POINT","partTopo":null,"points":[{"x":127.27266540725905,"y":37.679977265553894}]},"fieldValues":["19","0","[B@674c7e3e","26","80","천마산","812.0","0.0","41360262","오남읍"],"ID":19},{"stringID":null,"fieldNames":["SMID","SMUSERID","SMGEOMETRY","OBJ_ID","MNTN_ID","MNTN_NM","MNTN_HGHT","PHTGR_NO","EMNDN_CD","EMNDN_NM"],"geometry":{"center":{"x":126.96969296809252,"y":37.941344042198104},"parts":[1],"style":null,"prjCoordSys":null,"id":20,"type":"POINT","partTopo":null,"points":[{"x":126.96969296809252,"y":37.941344042198104}]},"fieldValues":["20","0","[B@69ff9524","27","5","감악산","675.0","0.0","41480370","적성면"],"ID":20},{"stringID":null,"fieldNames":["SMID","SMUSERID","SMGEOMETRY","OBJ_ID","MNTN_ID","MNTN_NM","MNTN_HGHT","PHTGR_NO","EMNDN_CD","EMNDN_NM"],"geometry":{"center":{"x":127.01049726986881,"y":37.696856053032526},"parts":[1],"style":null,"prjCoordSys":null,"id":21,"type":"POINT","partTopo":null,"points":[{"x":127.01049726986881,"y":37.696856053032526}]},"fieldValues":["21","0","[B@92e9355","28","27","도봉산","740.0","0.0","41630340","장흥면"],"ID":21},{"stringID":null,"fieldNames":["SMID","SMUSERID","SMGEOMETRY","OBJ_ID","MNTN_ID","MNTN_NM","MNTN_HGHT","PHTGR_NO","EMNDN_CD","EMNDN_NM"],"geometry":{"center":{"x":127.44429505225361,"y":38.07489438371278},"parts":[1],"style":null,"prjCoordSys":null,"id":22,"type":"POINT","partTopo":null,"points":[{"x":127.44429505225361,"y":38.07489438371278}]},"fieldValues":["22","0","[B@4c265bbf","29","43","백운산(포천)","904.0","0.0","41650380","이동면"],"ID":22},{"stringID":null,"fieldNames":["SMID","SMUSERID","SMGEOMETRY","OBJ_ID","MNTN_ID","MNTN_NM","MNTN_HGHT","PHTGR_NO","EMNDN_CD","EMNDN_NM"],"geometry":{"center":{"x":127.4321316473777,"y":37.941382829608756},"parts":[1],"style":null,"prjCoordSys":null,"id":23,"type":"POINT","partTopo":null,"points":[{"x":127.4321316473777,"y":37.941382829608756}]},"fieldValues":["23","0","[B@489f618b","31","33","명지산","1267.0","0.0","41820350","북면"],"ID":23},{"stringID":null,"fieldNames":["SMID","SMUSERID","SMGEOMETRY","OBJ_ID","MNTN_ID","MNTN_NM","MNTN_HGHT","PHTGR_NO","EMNDN_CD","EMNDN_NM"],"geometry":{"center":{"x":127.50376118673293,"y":37.995270893331565},"parts":[1],"style":null,"prjCoordSys":null,"id":24,"type":"POINT","partTopo":null,"points":[{"x":127.50376118673293,"y":37.995270893331565}]},"fieldValues":["24","0","[B@5d5c8b09","32","94","화악산","1468.0","0.0","41820350","북면"],"ID":24},{"stringID":null,"fieldNames":["SMID","SMUSERID","SMGEOMETRY","OBJ_ID","MNTN_ID","MNTN_NM","MNTN_HGHT","PHTGR_NO","EMNDN_CD","EMNDN_NM"],"geometry":{"center":{"x":127.54567205710163,"y":37.56112825144255},"parts":[1],"style":null,"prjCoordSys":null,"id":25,"type":"POINT","partTopo":null,"points":[{"x":127.54567205710163,"y":37.56112825144255}]},"fieldValues":["25","0","[B@20951fcc","34","61","용문산","1157.0","0.0","41830400","용문면"],"ID":25},{"stringID":null,"fieldNames":["SMID","SMUSERID","SMGEOMETRY","OBJ_ID","MNTN_ID","MNTN_NM","MNTN_HGHT","PHTGR_NO","EMNDN_CD","EMNDN_NM"],"geometry":{"center":{"x":128.53553010284406,"y":35.210050542282886},"parts":[1],"style":null,"prjCoordSys":null,"id":26,"type":"POINT","partTopo":null,"points":[{"x":128.53553010284406,"y":35.210050542282886}]},"fieldValues":["26","0","[B@5e1053c2","35","36","무학산","761.0","0.0","48160162","두척동"],"ID":26},{"stringID":null,"fieldNames":["SMID","SMUSERID","SMGEOMETRY","OBJ_ID","MNTN_ID","MNTN_NM","MNTN_HGHT","PHTGR_NO","EMNDN_CD","EMNDN_NM"],"geometry":{"center":{"x":128.41614868893151,"y":34.81042199185728},"parts":[1],"style":null,"prjCoordSys":null,"id":27,"type":"POINT","partTopo":null,"points":[{"x":128.41614868893151,"y":34.81042199185728}]},"fieldValues":["27","0","[B@6d30e2b2","36","37","미륵산","461.0","0.0","48220310","용남면"],"ID":27},{"stringID":null,"fieldNames":["SMID","SMUSERID","SMGEOMETRY","OBJ_ID","MNTN_ID","MNTN_NM","MNTN_HGHT","PHTGR_NO","EMNDN_CD","EMNDN_NM"],"geometry":{"center":{"x":128.1853167083938,"y":34.846026432550566},"parts":[1],"style":null,"prjCoordSys":null,"id":28,"type":"POINT","partTopo":null,"points":[{"x":128.1853167083938,"y":34.846026432550566}]},"fieldValues":["28","0","[B@540d28de","37","78","지리산(통영)","398.0","0.0","48220370","사량면"],"ID":28},{"stringID":null,"fieldNames":["SMID","SMUSERID","SMGEOMETRY","OBJ_ID","MNTN_ID","MNTN_NM","MNTN_HGHT","PHTGR_NO","EMNDN_CD","EMNDN_NM"],"geometry":{"center":{"x":128.9595335240719,"y":35.61568760888703},"parts":[1],"style":null,"prjCoordSys":null,"id":29,"type":"POINT","partTopo":null,"points":[{"x":128.9595335240719,"y":35.61568760888703}]},"fieldValues":["29","0","[B@5c6e36ec","38","63","운문산","1188.0","0.0","48270340","산내면"],"ID":29},{"stringID":null,"fieldNames":["SMID","SMUSERID","SMGEOMETRY","OBJ_ID","MNTN_ID","MNTN_NM","MNTN_HGHT","PHTGR_NO","EMNDN_CD","EMNDN_NM"],"geometry":{"center":{"x":129.05059247481125,"y":35.280149439275974},"parts":[1],"style":null,"prjCoordSys":null,"id":30,"type":"POINT","partTopo":null,"points":[{"x":129.05059247481125,"y":35.280149439275974}]},"fieldValues":["30","0","[B@bcf0e0","40","15","금정산","802.0","0.0","48330310","동면"],"ID":30},{"stringID":null,"fieldNames":["SMID","SMUSERID","SMGEOMETRY","OBJ_ID","MNTN_ID","MNTN_NM","MNTN_HGHT","PHTGR_NO","EMNDN_CD","EMNDN_NM"],"geometry":{"center":{"x":128.53252787704136,"y":35.54676623137845},"parts":[1],"style":null,"prjCoordSys":null,"id":31,"type":"POINT","partTopo":null,"points":[{"x":128.53252787704136,"y":35.54676623137845}]},"fieldValues":["31","0","[B@6a73a737","42","95","화왕산","757.0","0.0","48740250","창녕읍"],"ID":31},{"stringID":null,"fieldNames":["SMID","SMUSERID","SMGEOMETRY","OBJ_ID","MNTN_ID","MNTN_NM","MNTN_HGHT","PHTGR_NO","EMNDN_CD","EMNDN_NM"],"geometry":{"center":{"x":128.26497245309537,"y":35.070960679968266},"parts":[1],"style":null,"prjCoordSys":null,"id":32,"type":"POINT","partTopo":null,"points":[{"x":128.26497245309537,"y":35.070960679968266}]},"fieldValues":["32","0","[B@5705297f","43","58","연화산","528.0","0.0","48820380","개천면"],"ID":32},{"stringID":null,"fieldNames":["SMID","SMUSERID","SMGEOMETRY","OBJ_ID","MNTN_ID","MNTN_NM","MNTN_HGHT","PHTGR_NO","EMNDN_CD","EMNDN_NM"],"geometry":{"center":{"x":128.16307418153832,"y":35.7760614653925},"parts":[1],"style":null,"prjCoordSys":null,"id":33,"type":"POINT","partTopo":null,"points":[{"x":128.16307418153832,"y":35.7760614653925}]},"fieldValues":["33","0","[B@7af1bc25","44","1","가야산","1430.0","0.0","48890330","가야면"],"ID":33},{"stringID":null,"fieldNames":["SMID","SMUSERID","SMGEOMETRY","OBJ_ID","MNTN_ID","MNTN_NM","MNTN_HGHT","PHTGR_NO","EMNDN_CD","EMNDN_NM"],"geometry":{"center":{"x":127.97438998833401,"y":35.49508851649305},"parts":[1],"style":null,"prjCoordSys":null,"id":34,"type":"POINT","partTopo":null,"points":[{"x":127.97438998833401,"y":35.49508851649305}]},"fieldValues":["34","0","[B@1d2d686b","45","96","황매산","1108.0","0.0","48860310","차황면"],"ID":34},{"stringID":null,"fieldNames":["SMID","SMUSERID","SMGEOMETRY","OBJ_ID","MNTN_ID","MNTN_NM","MNTN_HGHT","PHTGR_NO","EMNDN_CD","EMNDN_NM"],"geometry":{"center":{"x":127.73059999391832,"y":35.3370747033326},"parts":[1],"style":null,"prjCoordSys":null,"id":35,"type":"POINT","partTopo":null,"points":[{"x":127.73059999391832,"y":35.3370747033326}]},"fieldValues":["35","0","[B@6a103ee6","46","77","지리산","1915.0","0.0","48870310","마천면"],"ID":35},{"stringID":null,"fieldNames":["SMID","SMUSERID","SMGEOMETRY","OBJ_ID","MNTN_ID","MNTN_NM","MNTN_HGHT","PHTGR_NO","EMNDN_CD","EMNDN_NM"],"geometry":{"center":{"x":127.75542766325341,"y":35.655188384920955},"parts":[1],"style":null,"prjCoordSys":null,"id":36,"type":"POINT","partTopo":null,"points":[{"x":127.75542766325341,"y":35.655188384920955}]},"fieldValues":["36","0","[B@14a0ac0a","47","97","황석산","1190.0","0.0","48870360","안의면"],"ID":36},{"stringID":null,"fieldNames":["SMID","SMUSERID","SMGEOMETRY","OBJ_ID","MNTN_ID","MNTN_NM","MNTN_HGHT","PHTGR_NO","EMNDN_CD","EMNDN_NM"],"geometry":{"center":{"x":129.26428743766223,"y":35.837884122919206},"parts":[1],"style":null,"prjCoordSys":null,"id":37,"type":"POINT","partTopo":null,"points":[{"x":129.26428743766223,"y":35.837884122919206}]},"fieldValues":["37","0","[B@63c73a2f","50","17","남산","468.0","0.0","47130122","구황동"],"ID":37},{"stringID":null,"fieldNames":["SMID","SMUSERID","SMGEOMETRY","OBJ_ID","MNTN_ID","MNTN_NM","MNTN_HGHT","PHTGR_NO","EMNDN_CD","EMNDN_NM"],"geometry":{"center":{"x":128.29982883576946,"y":36.09160809439772},"parts":[1],"style":null,"prjCoordSys":null,"id":38,"type":"POINT","partTopo":null,"points":[{"x":128.29982883576946,"y":36.09160809439772}]},"fieldValues":["38","0","[B@15df780c","51","14","금오산","977.0","0.0","47190108","남통동"],"ID":38},{"stringID":null,"fieldNames":["SMID","SMUSERID","SMGEOMETRY","OBJ_ID","MNTN_ID","MNTN_NM","MNTN_HGHT","PHTGR_NO","EMNDN_CD","EMNDN_NM"],"geometry":{"center":{"x":128.27795653758324,"y":36.812523710373746},"parts":[1],"style":null,"prjCoordSys":null,"id":39,"type":"POINT","partTopo":null,"points":[{"x":128.27795653758324,"y":36.812523710373746}]},"fieldValues":["39","0","[B@7ed3835f","52","99","황장산","1077.0","0.0","47280350","동로면"],"ID":39},{"stringID":null,"fieldNames":["SMID","SMUSERID","SMGEOMETRY","OBJ_ID","MNTN_ID","MNTN_NM","MNTN_HGHT","PHTGR_NO","EMNDN_CD","EMNDN_NM"],"geometry":{"center":{"x":128.10093682404036,"y":36.78825867409735},"parts":[1],"style":null,"prjCoordSys":null,"id":40,"type":"POINT","partTopo":null,"points":[{"x":128.10093682404036,"y":36.78825867409735}]},"fieldValues":["40","0","[B@6f82b073","53","76","주흘산","1106.0","0.0","47280250","문경읍"],"ID":40},{"stringID":null,"fieldNames":["SMID","SMUSERID","SMGEOMETRY","OBJ_ID","MNTN_ID","MNTN_NM","MNTN_HGHT","PHTGR_NO","EMNDN_CD","EMNDN_NM"],"geometry":{"center":{"x":129.16274449469657,"y":36.38952455956733},"parts":[1],"style":null,"prjCoordSys":null,"id":41,"type":"POINT","partTopo":null,"points":[{"x":129.16274449469657,"y":36.38952455956733}]},"fieldValues":["41","0","[B@354ef9ee","54","75","주왕산","721.0","0.0","47750310","부동면"],"ID":41},{"stringID":null,"fieldNames":["SMID","SMUSERID","SMGEOMETRY","OBJ_ID","MNTN_ID","MNTN_NM","MNTN_HGHT","PHTGR_NO","EMNDN_CD","EMNDN_NM"],"geometry":{"center":{"x":129.28940254035976,"y":36.27889397517117},"parts":[1],"style":null,"prjCoordSys":null,"id":42,"type":"POINT","partTopo":null,"points":[{"x":129.28940254035976,"y":36.27889397517117}]},"fieldValues":["42","0","[B@5b3ff853","55","18","내연산","710.0","0.0","47770320","남정면"],"ID":42},{"stringID":null,"fieldNames":["SMID","SMUSERID","SMGEOMETRY","OBJ_ID","MNTN_ID","MNTN_NM","MNTN_HGHT","PHTGR_NO","EMNDN_CD","EMNDN_NM"],"geometry":{"center":{"x":129.00233152563774,"y":35.620115656364575},"parts":[1],"style":null,"prjCoordSys":null,"id":43,"type":"POINT","partTopo":null,"points":[{"x":129.00233152563774,"y":35.620115656364575}]},"fieldValues":["43","0","[B@39144110","56","4","가지산","1240.0","0.0","47820350","운문면"],"ID":43},{"stringID":null,"fieldNames":["SMID","SMUSERID","SMGEOMETRY","OBJ_ID","MNTN_ID","MNTN_NM","MNTN_HGHT","PHTGR_NO","EMNDN_CD","EMNDN_NM"],"geometry":{"center":{"x":127.00888909751231,"y":35.12433829134472},"parts":[1],"style":null,"prjCoordSys":null,"id":44,"type":"POINT","partTopo":null,"points":[{"x":127.00888909751231,"y":35.12433829134472}]},"fieldValues":["44","0","[B@43ef7f69","58","35","무등산","1187.0","0.0","29170120","금곡동"],"ID":44},{"stringID":null,"fieldNames":["SMID","SMUSERID","SMGEOMETRY","OBJ_ID","MNTN_ID","MNTN_NM","MNTN_HGHT","PHTGR_NO","EMNDN_CD","EMNDN_NM"],"geometry":{"center":{"x":128.69455391713677,"y":36.016289712488714},"parts":[1],"style":null,"prjCoordSys":null,"id":45,"type":"POINT","partTopo":null,"points":[{"x":128.69455391713677,"y":36.016289712488714}]},"fieldValues":["45","0","[B@12c7f73","59","90","팔공산","1193.0","0.0","27140134","도학동"],"ID":45},{"stringID":null,"fieldNames":["SMID","SMUSERID","SMGEOMETRY","OBJ_ID","MNTN_ID","MNTN_NM","MNTN_HGHT","PHTGR_NO","EMNDN_CD","EMNDN_NM"],"geometry":{"center":{"x":128.52425977587555,"y":35.715609655003256},"parts":[1],"style":null,"prjCoordSys":null,"id":46,"type":"POINT","partTopo":null,"points":[{"x":128.52425977587555,"y":35.715609655003256}]},"fieldValues":["46","0","[B@2575e265","60","48","비슬산","1084.0","0.0","27710370","유가면"],"ID":46},{"stringID":null,"fieldNames":["SMID","SMUSERID","SMGEOMETRY","OBJ_ID","MNTN_ID","MNTN_NM","MNTN_HGHT","PHTGR_NO","EMNDN_CD","EMNDN_NM"],"geometry":{"center":{"x":126.96295961954957,"y":37.44107570463481},"parts":[1],"style":null,"prjCoordSys":null,"id":47,"type":"POINT","partTopo":null,"points":[{"x":126.96295961954957,"y":37.44107570463481}]},"fieldValues":["47","0","[B@3e722b1a","61","10","관악산","629.0","0.0","11620102","신림동"],"ID":47},{"stringID":null,"fieldNames":["SMID","SMUSERID","SMGEOMETRY","OBJ_ID","MNTN_ID","MNTN_NM","MNTN_HGHT","PHTGR_NO","EMNDN_CD","EMNDN_NM"],"geometry":{"center":{"x":126.43464112863053,"y":37.612629219009264},"parts":[1],"style":null,"prjCoordSys":null,"id":48,"type":"POINT","partTopo":null,"points":[{"x":126.43464112863053,"y":37.612629219009264}]},"fieldValues":["48","0","[B@65e1f8a","63","30","마니산","469.0","0.0","28710340","화도면"],"ID":48},{"stringID":null,"fieldNames":["SMID","SMUSERID","SMGEOMETRY","OBJ_ID","MNTN_ID","MNTN_NM","MNTN_HGHT","PHTGR_NO","EMNDN_CD","EMNDN_NM"],"geometry":{"center":{"x":127.31348735665475,"y":35.00118197990586},"parts":[1],"style":null,"prjCoordSys":null,"id":49,"type":"POINT","partTopo":null,"points":[{"x":127.31348735665475,"y":35.00118197990586}]},"fieldValues":["49","0","[B@64eb3fd5","65","74","조계산","884.0","0.0","46150250","승주읍"],"ID":49},{"stringID":null,"fieldNames":["SMID","SMUSERID","SMGEOMETRY","OBJ_ID","MNTN_ID","MNTN_NM","MNTN_HGHT","PHTGR_NO","EMNDN_CD","EMNDN_NM"],"geometry":{"center":{"x":127.62111722315615,"y":35.106219627366116},"parts":[1],"style":null,"prjCoordSys":null,"id":50,"type":"POINT","partTopo":null,"points":[{"x":127.62111722315615,"y":35.106219627366116}]},"fieldValues":["50","0","[B@6e878fe7","66","44","백운산(광양)","1218.0","0.0","46230360","다압면"],"ID":50},{"stringID":null,"fieldNames":["SMID","SMUSERID","SMGEOMETRY","OBJ_ID","MNTN_ID","MNTN_NM","MNTN_HGHT","PHTGR_NO","EMNDN_CD","EMNDN_NM"],"geometry":{"center":{"x":127.04983940624673,"y":35.40356945398713},"parts":[1],"style":null,"prjCoordSys":null,"id":51,"type":"POINT","partTopo":null,"points":[{"x":127.04983940624673,"y":35.40356945398713}]},"fieldValues":["51","0","[B@418243d6","67","6","강천산","584.0","0.0","46710380","용면"],"ID":51},{"stringID":null,"fieldNames":["SMID","SMUSERID","SMGEOMETRY","OBJ_ID","MNTN_ID","MNTN_NM","MNTN_HGHT","PHTGR_NO","EMNDN_CD","EMNDN_NM"],"geometry":{"center":{"x":127.43576965245845,"y":34.617373487172095},"parts":[1],"style":null,"prjCoordSys":null,"id":52,"type":"POINT","partTopo":null,"points":[{"x":127.43576965245845,"y":34.617373487172095}]},"fieldValues":["52","0","[B@3756b623","68","92","팔영산","609.0","0.0","46770440","영남면"],"ID":52},{"stringID":null,"fieldNames":["SMID","SMUSERID","SMGEOMETRY","OBJ_ID","MNTN_ID","MNTN_NM","MNTN_HGHT","PHTGR_NO","EMNDN_CD","EMNDN_NM"],"geometry":{"center":{"x":126.63654649275635,"y":34.47319857838312},"parts":[1],"style":null,"prjCoordSys":null,"id":53,"type":"POINT","partTopo":null,"points":[{"x":126.63654649275635,"y":34.47319857838312}]},"fieldValues":["53","0","[B@afe228b","69","28","두륜산","703.0","0.0","46820310","삼산면"],"ID":53},{"stringID":null,"fieldNames":["SMID","SMUSERID","SMGEOMETRY","OBJ_ID","MNTN_ID","MNTN_NM","MNTN_HGHT","PHTGR_NO","EMNDN_CD","EMNDN_NM"],"geometry":{"center":{"x":126.86877382045746,"y":35.460687013804666},"parts":[1],"style":null,"prjCoordSys":null,"id":54,"type":"POINT","partTopo":null,"points":[{"x":126.86877382045746,"y":35.460687013804666}]},"fieldValues":["54","0","[B@58d46c84","71","42","백암산","741.0","0.0","46880400","북하면"],"ID":54},{"stringID":null,"fieldNames":["SMID","SMUSERID","SMGEOMETRY","OBJ_ID","MNTN_ID","MNTN_NM","MNTN_HGHT","PHTGR_NO","EMNDN_CD","EMNDN_NM"],"geometry":{"center":{"x":125.20419722588856,"y":34.697100349659785},"parts":[1],"style":null,"prjCoordSys":null,"id":55,"type":"POINT","partTopo":null,"points":[{"x":125.20419722588856,"y":34.697100349659785}]},"fieldValues":["55","0","[B@b9b18bb","72","16","깃대봉","368.0","0.0","46910360","흑산면"],"ID":55},{"stringID":null,"fieldNames":["SMID","SMUSERID","SMGEOMETRY","OBJ_ID","MNTN_ID","MNTN_NM","MNTN_HGHT","PHTGR_NO","EMNDN_CD","EMNDN_NM"],"geometry":{"center":{"x":127.68952183186948,"y":35.94635456787954},"parts":[1],"style":null,"prjCoordSys":null,"id":56,"type":"POINT","partTopo":null,"points":[{"x":127.68952183186948,"y":35.94635456787954}]},"fieldValues":["56","0","[B@97e5045","74","72","적상산","1034.0","0.0","52730330","적상면"],"ID":56},{"stringID":null,"fieldNames":["SMID","SMUSERID","SMGEOMETRY","OBJ_ID","MNTN_ID","MNTN_NM","MNTN_HGHT","PHTGR_NO","EMNDN_CD","EMNDN_NM"],"geometry":{"center":{"x":127.08510225373016,"y":35.728077215140424},"parts":[1],"style":null,"prjCoordSys":null,"id":57,"type":"POINT","partTopo":null,"points":[{"x":127.08510225373016,"y":35.728077215140424}]},"fieldValues":["57","0","[B@726fc19b","75","34","모악산","794.0","0.0","52210450","금산면"],"ID":57},{"stringID":null,"fieldNames":["SMID","SMUSERID","SMGEOMETRY","OBJ_ID","MNTN_ID","MNTN_NM","MNTN_HGHT","PHTGR_NO","EMNDN_CD","EMNDN_NM"],"geometry":{"center":{"x":127.31933647280219,"y":36.123397200191015},"parts":[1],"style":null,"prjCoordSys":null,"id":58,"type":"POINT","partTopo":null,"points":[{"x":127.31933647280219,"y":36.123397200191015}]},"fieldValues":["58","0","[B@9a4231e","76","20","대둔산","878.0","0.0","52710380","운주면"],"ID":58},{"stringID":null,"fieldNames":["SMID","SMUSERID","SMGEOMETRY","OBJ_ID","MNTN_ID","MNTN_NM","MNTN_HGHT","PHTGR_NO","EMNDN_CD","EMNDN_NM"],"geometry":{"center":{"x":127.35760521260731,"y":35.911389769705906},"parts":[1],"style":null,"prjCoordSys":null,"id":59,"type":"POINT","partTopo":null,"points":[{"x":127.35760521260731,"y":35.911389769705906}]},"fieldValues":["59","0","[B@5a29ac51","77","65","운장산","1126.0","0.0","52710400","동상면"],"ID":59},{"stringID":null,"fieldNames":["SMID","SMUSERID","SMGEOMETRY","OBJ_ID","MNTN_ID","MNTN_NM","MNTN_HGHT","PHTGR_NO","EMNDN_CD","EMNDN_NM"],"geometry":{"center":{"x":127.59481089872851,"y":35.6291627756415},"parts":[1],"style":null,"prjCoordSys":null,"id":60,"type":"POINT","partTopo":null,"points":[{"x":127.59481089872851,"y":35.6291627756415}]},"fieldValues":["60","0","[B@212e2329","79","70","장안산","1237.0","0.0","52740250","장수읍"],"ID":60},{"stringID":null,"fieldNames":["SMID","SMUSERID","SMGEOMETRY","OBJ_ID","MNTN_ID","MNTN_NM","MNTN_HGHT","PHTGR_NO","EMNDN_CD","EMNDN_NM"],"geometry":{"center":{"x":126.88918533667449,"y":35.47821546750881},"parts":[1],"style":null,"prjCoordSys":null,"id":61,"type":"POINT","partTopo":null,"points":[{"x":126.88918533667449,"y":35.47821546750881}]},"fieldValues":["61","0","[B@2dc14d8e","80","19","내장산","763.0","0.0","52770370","복흥면"],"ID":61},{"stringID":null,"fieldNames":["SMID","SMUSERID","SMGEOMETRY","OBJ_ID","MNTN_ID","MNTN_NM","MNTN_HGHT","PHTGR_NO","EMNDN_CD","EMNDN_NM"],"geometry":{"center":{"x":126.97630281537134,"y":35.400068761213255},"parts":[1],"style":null,"prjCoordSys":null,"id":62,"type":"POINT","partTopo":null,"points":[{"x":126.97630281537134,"y":35.400068761213255}]},"fieldValues":["62","0","[B@5d527fb","81","84","추월산","731.0","0.0","52770370","복흥면"],"ID":62},{"stringID":null,"fieldNames":["SMID","SMUSERID","SMGEOMETRY","OBJ_ID","MNTN_ID","MNTN_NM","MNTN_HGHT","PHTGR_NO","EMNDN_CD","EMNDN_NM"],"geometry":{"center":{"x":126.51066314051683,"y":35.48068599770202},"parts":[1],"style":null,"prjCoordSys":null,"id":63,"type":"POINT","partTopo":null,"points":[{"x":126.51066314051683,"y":35.48068599770202}]},"fieldValues":["63","0","[B@12895834","83","51","선운산","336.0","0.0","52790360","해리면"],"ID":63},{"stringID":null,"fieldNames":["SMID","SMUSERID","SMGEOMETRY","OBJ_ID","MNTN_ID","MNTN_NM","MNTN_HGHT","PHTGR_NO","EMNDN_CD","EMNDN_NM"],"geometry":{"center":{"x":126.62175137020935,"y":35.635588214649474},"parts":[1],"style":null,"prjCoordSys":null,"id":64,"type":"POINT","partTopo":null,"points":[{"x":126.62175137020935,"y":35.635588214649474}]},"fieldValues":["64","0","[B@426e1627","84","46","변산","508.0","0.0","52800390","상서면"],"ID":64},{"stringID":null,"fieldNames":["SMID","SMUSERID","SMGEOMETRY","OBJ_ID","MNTN_ID","MNTN_NM","MNTN_HGHT","PHTGR_NO","EMNDN_CD","EMNDN_NM"],"geometry":{"center":{"x":126.52998077415303,"y":33.36128098469411},"parts":[1],"style":null,"prjCoordSys":null,"id":65,"type":"POINT","partTopo":null,"points":[{"x":126.52998077415303,"y":33.36128098469411}]},"fieldValues":["65","0","[B@65e48ed9","85","93","한라산","1950.0","1.0","50130122","영남동"],"ID":65},{"stringID":null,"fieldNames":["SMID","SMUSERID","SMGEOMETRY","OBJ_ID","MNTN_ID","MNTN_NM","MNTN_HGHT","PHTGR_NO","EMNDN_CD","EMNDN_NM"],"geometry":{"center":{"x":127.20573349073513,"y":36.3422816669749},"parts":[1],"style":null,"prjCoordSys":null,"id":66,"type":"POINT","partTopo":null,"points":[{"x":127.20573349073513,"y":36.3422816669749}]},"fieldValues":["66","0","[B@49229761","87","7","계룡산","845.0","0.0","44150330","계룡면"],"ID":66},{"stringID":null,"fieldNames":["SMID","SMUSERID","SMGEOMETRY","OBJ_ID","MNTN_ID","MNTN_NM","MNTN_HGHT","PHTGR_NO","EMNDN_CD","EMNDN_NM"],"geometry":{"center":{"x":127.53834143079285,"y":36.22072449928958},"parts":[1],"style":null,"prjCoordSys":null,"id":67,"type":"POINT","partTopo":null,"points":[{"x":127.53834143079285,"y":36.22072449928958}]},"fieldValues":["67","0","[B@11b22e89","88","50","서대산","904.0","0.0","44710390","추부면"],"ID":67},{"stringID":null,"fieldNames":["SMID","SMUSERID","SMGEOMETRY","OBJ_ID","MNTN_ID","MNTN_NM","MNTN_HGHT","PHTGR_NO","EMNDN_CD","EMNDN_NM"],"geometry":{"center":{"x":127.59994438024209,"y":36.159212833755184},"parts":[1],"style":null,"prjCoordSys":null,"id":68,"type":"POINT","partTopo":null,"points":[{"x":127.59994438024209,"y":36.159212833755184}]},"fieldValues":["68","0","[B@235fcdb6","89","82","천태산","715.0","0.0","44710320","제원면"],"ID":68},{"stringID":null,"fieldNames":["SMID","SMUSERID","SMGEOMETRY","OBJ_ID","MNTN_ID","MNTN_NM","MNTN_HGHT","PHTGR_NO","EMNDN_CD","EMNDN_NM"],"geometry":{"center":{"x":127.84910995389845,"y":36.03939911973876},"parts":[1],"style":null,"prjCoordSys":null,"id":69,"type":"POINT","partTopo":null,"points":[{"x":127.84910995389845,"y":36.03939911973876}]},"fieldValues":["69","0","[B@628c0d42","90","38","민주지산","1242.0","0.0","44710330","부리면"],"ID":69},{"stringID":null,"fieldNames":["SMID","SMUSERID","SMGEOMETRY","OBJ_ID","MNTN_ID","MNTN_NM","MNTN_HGHT","PHTGR_NO","EMNDN_CD","EMNDN_NM"],"geometry":{"center":{"x":126.62399767196106,"y":36.671466313943995},"parts":[1],"style":null,"prjCoordSys":null,"id":70,"type":"POINT","partTopo":null,"points":[{"x":126.62399767196106,"y":36.671466313943995}]},"fieldValues":["70","0","[B@3f4817ed","91","23","덕숭산","495.0","0.0","44810360","덕산면"],"ID":70},{"stringID":null,"fieldNames":["SMID","SMUSERID","SMGEOMETRY","OBJ_ID","MNTN_ID","MNTN_NM","MNTN_HGHT","PHTGR_NO","EMNDN_CD","EMNDN_NM"],"geometry":{"center":{"x":128.10564332219667,"y":36.88578398459032},"parts":[1],"style":null,"prjCoordSys":null,"id":71,"type":"POINT","partTopo":null,"points":[{"x":128.10564332219667,"y":36.88578398459032}]},"fieldValues":["71","0","[B@3f8ea0eb","93","66","월악산","1094.0","0.0","43150350","한수면"],"ID":71},{"stringID":null,"fieldNames":["SMID","SMUSERID","SMGEOMETRY","OBJ_ID","MNTN_ID","MNTN_NM","MNTN_HGHT","PHTGR_NO","EMNDN_CD","EMNDN_NM"],"geometry":{"center":{"x":128.31107007733812,"y":36.856387996579684},"parts":[1],"style":null,"prjCoordSys":null,"id":72,"type":"POINT","partTopo":null,"points":[{"x":128.31107007733812,"y":36.856387996579684}]},"fieldValues":["72","0","[B@62e1f8d1","95","26","도락산","964.0","0.0","43800360","단성면"],"ID":72},{"stringID":null,"fieldNames":["SMID","SMUSERID","SMGEOMETRY","OBJ_ID","MNTN_ID","MNTN_NM","MNTN_HGHT","PHTGR_NO","EMNDN_CD","EMNDN_NM"],"geometry":{"center":{"x":127.87045000709074,"y":36.54274699386788},"parts":[1],"style":null,"prjCoordSys":null,"id":73,"type":"POINT","partTopo":null,"points":[{"x":127.87045000709074,"y":36.54274699386788}]},"fieldValues":["73","0","[B@60851fd2","96","56","속리산","1057.0","0.0","43720310","내속리면"],"ID":73},{"stringID":null,"fieldNames":["SMID","SMUSERID","SMGEOMETRY","OBJ_ID","MNTN_ID","MNTN_NM","MNTN_HGHT","PHTGR_NO","EMNDN_CD","EMNDN_NM"],"geometry":{"center":{"x":127.86200698944201,"y":36.46947824218034},"parts":[1],"style":null,"prjCoordSys":null,"id":74,"type":"POINT","partTopo":null,"points":[{"x":127.86200698944201,"y":36.46947824218034}]},"fieldValues":["74","0","[B@1f8d9b50","97","11","구병산","877.0","0.0","43720310","내속리면"],"ID":74},{"stringID":null,"fieldNames":["SMID","SMUSERID","SMGEOMETRY","OBJ_ID","MNTN_ID","MNTN_NM","MNTN_HGHT","PHTGR_NO","EMNDN_CD","EMNDN_NM"],"geometry":{"center":{"x":127.96626085624351,"y":36.11829516174446},"parts":[1],"style":null,"prjCoordSys":null,"id":75,"type":"POINT","partTopo":null,"points":[{"x":127.96626085624351,"y":36.11829516174446}]},"fieldValues":["75","0","[B@55cef9b2","98","98","황악산","1111.0","0.0","43740340","매곡면"],"ID":75},{"stringID":null,"fieldNames":["SMID","SMUSERID","SMGEOMETRY","OBJ_ID","MNTN_ID","MNTN_NM","MNTN_HGHT","PHTGR_NO","EMNDN_CD","EMNDN_NM"],"geometry":{"center":{"x":128.0046136501346,"y":36.71476280253933},"parts":[1],"style":null,"prjCoordSys":null,"id":76,"type":"POINT","partTopo":null,"points":[{"x":128.0046136501346,"y":36.71476280253933}]},"fieldValues":["76","0","[B@3804a4aa","99","100","희양산","999.0","0.0","43760330","연풍면"],"ID":76},{"stringID":null,"fieldNames":["SMID","SMUSERID","SMGEOMETRY","OBJ_ID","MNTN_ID","MNTN_NM","MNTN_HGHT","PHTGR_NO","EMNDN_CD","EMNDN_NM"],"geometry":{"center":{"x":127.92941350323085,"y":36.66895923130192},"parts":[1],"style":null,"prjCoordSys":null,"id":77,"type":"POINT","partTopo":null,"points":[{"x":127.92941350323085,"y":36.66895923130192}]},"fieldValues":["77","0","[B@703747f7","100","22","대야산","931.0","0.0","43760360","청천면"],"ID":77},{"stringID":null,"fieldNames":["SMID","SMUSERID","SMGEOMETRY","OBJ_ID","MNTN_ID","MNTN_NM","MNTN_HGHT","PHTGR_NO","EMNDN_CD","EMNDN_NM"],"geometry":{"center":{"x":128.38999949102006,"y":37.88829194472804},"parts":[1],"style":null,"prjCoordSys":null,"id":78,"type":"POINT","partTopo":null,"points":[{"x":128.38999949102006,"y":37.88829194472804}]},"fieldValues":["78","0","[B@39315ba","10","40","방태산","1444.0","0.0","51810350","상남면"],"ID":78},{"stringID":null,"fieldNames":["SMID","SMUSERID","SMGEOMETRY","OBJ_ID","MNTN_ID","MNTN_NM","MNTN_HGHT","PHTGR_NO","EMNDN_CD","EMNDN_NM"],"geometry":{"center":{"x":127.69656438122166,"y":37.69594881307573},"parts":[1],"style":null,"prjCoordSys":null,"id":79,"type":"POINT","partTopo":null,"points":[{"x":127.69656438122166,"y":37.69594881307573}]},"fieldValues":["79","0","[B@21b27f13","18","91","팔봉산","302.0","0.0","51720370","서면"],"ID":79},{"stringID":null,"fieldNames":["SMID","SMUSERID","SMGEOMETRY","OBJ_ID","MNTN_ID","MNTN_NM","MNTN_HGHT","PHTGR_NO","EMNDN_CD","EMNDN_NM"],"geometry":{"center":{"x":127.33394953259712,"y":37.75262785240715},"parts":[1],"style":null,"prjCoordSys":null,"id":80,"type":"POINT","partTopo":null,"points":[{"x":127.33394953259712,"y":37.75262785240715}]},"fieldValues":["80","0","[B@3c0eae7b","25","85","축령산","879.0","0.0","41360340","수동면"],"ID":80},{"stringID":null,"fieldNames":["SMID","SMUSERID","SMGEOMETRY","OBJ_ID","MNTN_ID","MNTN_NM","MNTN_HGHT","PHTGR_NO","EMNDN_CD","EMNDN_NM"],"geometry":{"center":{"x":127.48681082018597,"y":37.57539301910176},"parts":[1],"style":null,"prjCoordSys":null,"id":81,"type":"POINT","partTopo":null,"points":[{"x":127.48681082018597,"y":37.57539301910176}]},"fieldValues":["81","0","[B@764c4ef2","33","68","유명산","862.0","0.0","41820310","설악면"],"ID":81},{"stringID":null,"fieldNames":["SMID","SMUSERID","SMGEOMETRY","OBJ_ID","MNTN_ID","MNTN_NM","MNTN_HGHT","PHTGR_NO","EMNDN_CD","EMNDN_NM"],"geometry":{"center":{"x":128.985245801155,"y":35.330981352207694},"parts":[1],"style":null,"prjCoordSys":null,"id":82,"type":"POINT","partTopo":null,"points":[{"x":128.985245801155,"y":35.330981352207694}]},"fieldValues":["82","0","[B@6de9ab44","41","81","천성산","922.0","0.0","48330320","원동면"],"ID":82},{"stringID":null,"fieldNames":["SMID","SMUSERID","SMGEOMETRY","OBJ_ID","MNTN_ID","MNTN_NM","MNTN_HGHT","PHTGR_NO","EMNDN_CD","EMNDN_NM"],"geometry":{"center":{"x":130.86609240231437,"y":37.50076497863418},"parts":[1],"style":null,"prjCoordSys":null,"id":83,"type":"POINT","partTopo":null,"points":[{"x":130.86609240231437,"y":37.50076497863418}]},"fieldValues":["83","0","[B@5f110b0d","49","53","성인봉","984.0","0.0","47940310","서면"],"ID":83},{"stringID":null,"fieldNames":["SMID","SMUSERID","SMGEOMETRY","OBJ_ID","MNTN_ID","MNTN_NM","MNTN_HGHT","PHTGR_NO","EMNDN_CD","EMNDN_NM"],"geometry":{"center":{"x":129.05253866340553,"y":35.539734211353995},"parts":[1],"style":null,"prjCoordSys":null,"id":84,"type":"POINT","partTopo":null,"points":[{"x":129.05253866340553,"y":35.539734211353995}]},"fieldValues":["84","0","[B@16a51be2","62","57","신불산","1209.0","0.0","31710380","상북면"],"ID":84},{"stringID":null,"fieldNames":["SMID","SMUSERID","SMGEOMETRY","OBJ_ID","MNTN_ID","MNTN_NM","MNTN_HGHT","PHTGR_NO","EMNDN_CD","EMNDN_NM"],"geometry":{"center":{"x":127.41622089184575,"y":35.76108700101668},"parts":[1],"style":null,"prjCoordSys":null,"id":85,"type":"POINT","partTopo":null,"points":[{"x":127.41622089184575,"y":35.76108700101668}]},"fieldValues":["85","0","[B@20afc1a","78","31","마이산","686.0","0.0","52720250","진안읍"],"ID":85},{"stringID":null,"fieldNames":["SMID","SMUSERID","SMGEOMETRY","OBJ_ID","MNTN_ID","MNTN_NM","MNTN_HGHT","PHTGR_NO","EMNDN_CD","EMNDN_NM"],"geometry":{"center":{"x":126.88479158788348,"y":36.41286024272212},"parts":[1],"style":null,"prjCoordSys":null,"id":86,"type":"POINT","partTopo":null,"points":[{"x":126.88479158788348,"y":36.41286024272212}]},"fieldValues":["86","0","[B@2299d494","86","87","칠갑산","561.0","0.0","44790320","대치면"],"ID":86},{"stringID":null,"fieldNames":["SMID","SMUSERID","SMGEOMETRY","OBJ_ID","MNTN_ID","MNTN_NM","MNTN_HGHT","PHTGR_NO","EMNDN_CD","EMNDN_NM"],"geometry":{"center":{"x":129.2302090424472,"y":37.07654261788883},"parts":[1],"style":null,"prjCoordSys":null,"id":87,"type":"POINT","partTopo":null,"points":[{"x":129.2302090424472,"y":37.07654261788883}]},"fieldValues":["87","0","[B@7587eaa9","1","69","응봉산","999.0","0.0","51230350","가곡면"],"ID":87},{"stringID":null,"fieldNames":["SMID","SMUSERID","SMGEOMETRY","OBJ_ID","MNTN_ID","MNTN_NM","MNTN_HGHT","PHTGR_NO","EMNDN_CD","EMNDN_NM"],"geometry":{"center":{"x":128.46517898891142,"y":38.11899025977232},"parts":[1],"style":null,"prjCoordSys":null,"id":88,"type":"POINT","partTopo":null,"points":[{"x":128.46517898891142,"y":38.11899025977232}]},"fieldValues":["88","0","[B@4bc385f0","11","52","설악산","1708.0","0.0","51830310","서면"],"ID":88},{"stringID":null,"fieldNames":["SMID","SMUSERID","SMGEOMETRY","OBJ_ID","MNTN_ID","MNTN_NM","MNTN_HGHT","PHTGR_NO","EMNDN_CD","EMNDN_NM"],"geometry":{"center":{"x":127.74730014229955,"y":38.038245431823356},"parts":[1],"style":null,"prjCoordSys":null,"id":89,"type":"POINT","partTopo":null,"points":[{"x":127.74730014229955,"y":38.038245431823356}]},"fieldValues":["89","0","[B@1efc5abe","20","62","용화산","878.0","0.0","51790320","하남면"],"ID":89},{"stringID":null,"fieldNames":["SMID","SMUSERID","SMGEOMETRY","OBJ_ID","MNTN_ID","MNTN_NM","MNTN_HGHT","PHTGR_NO","EMNDN_CD","EMNDN_NM"],"geometry":{"center":{"x":127.32521144475446,"y":37.87681189432016},"parts":[1],"style":null,"prjCoordSys":null,"id":90,"type":"POINT","partTopo":null,"points":[{"x":127.32521144475446,"y":37.87681189432016}]},"fieldValues":["90","0","[B@72ad1081","30","64","운악산","936.0","0.0","41650410","화현면"],"ID":90},{"stringID":null,"fieldNames":["SMID","SMUSERID","SMGEOMETRY","OBJ_ID","MNTN_ID","MNTN_NM","MNTN_HGHT","PHTGR_NO","EMNDN_CD","EMNDN_NM"],"geometry":{"center":{"x":128.97090452278528,"y":35.560870443612714},"parts":[1],"style":null,"prjCoordSys":null,"id":91,"type":"POINT","partTopo":null,"points":[{"x":128.97090452278528,"y":35.560870443612714}]},"fieldValues":["91","0","[B@38b56edf","39","71","재약산","1189.0","0.0","48270340","산내면"],"ID":91},{"stringID":null,"fieldNames":["SMID","SMUSERID","SMGEOMETRY","OBJ_ID","MNTN_ID","MNTN_NM","MNTN_HGHT","PHTGR_NO","EMNDN_CD","EMNDN_NM"],"geometry":{"center":{"x":127.98038924789843,"y":34.7531074129588},"parts":[1],"style":null,"prjCoordSys":null,"id":92,"type":"POINT","partTopo":null,"points":[{"x":127.98038924789843,"y":34.7531074129588}]},"fieldValues":["92","0","[B@6f8e903c","48","12","금산","701.0","0.0","48840320","상주면"],"ID":92},{"stringID":null,"fieldNames":["SMID","SMUSERID","SMGEOMETRY","OBJ_ID","MNTN_ID","MNTN_NM","MNTN_HGHT","PHTGR_NO","EMNDN_CD","EMNDN_NM"],"geometry":{"center":{"x":128.9087801215278,"y":36.79433615776348},"parts":[1],"style":null,"prjCoordSys":null,"id":93,"type":"POINT","partTopo":null,"points":[{"x":128.9087801215278,"y":36.79433615776348}]},"fieldValues":["93","0","[B@135b1ed9","57","83","청량산","870.0","0.0","47920370","명호면"],"ID":93},{"stringID":null,"fieldNames":["SMID","SMUSERID","SMGEOMETRY","OBJ_ID","MNTN_ID","MNTN_NM","MNTN_HGHT","PHTGR_NO","EMNDN_CD","EMNDN_NM"],"geometry":{"center":{"x":126.91846615035432,"y":34.53160019672535},"parts":[1],"style":null,"prjCoordSys":null,"id":94,"type":"POINT","partTopo":null,"points":[{"x":126.91846615035432,"y":34.53160019672535}]},"fieldValues":["94","0","[B@9683d2b","64","79","천관산","723.0","0.0","46800256","대덕읍"],"ID":94},{"stringID":null,"fieldNames":["SMID","SMUSERID","SMGEOMETRY","OBJ_ID","MNTN_ID","MNTN_NM","MNTN_HGHT","PHTGR_NO","EMNDN_CD","EMNDN_NM"],"geometry":{"center":{"x":127.74632944441488,"y":35.85946525223085},"parts":[1],"style":null,"prjCoordSys":null,"id":95,"type":"POINT","partTopo":null,"points":[{"x":127.74632944441488,"y":35.85946525223085}]},"fieldValues":["95","0","[B@1ab8794f","73","24","덕유산","1614.0","0.0","52730340","안성면"],"ID":95},{"stringID":null,"fieldNames":["SMID","SMUSERID","SMGEOMETRY","OBJ_ID","MNTN_ID","MNTN_NM","MNTN_HGHT","PHTGR_NO","EMNDN_CD","EMNDN_NM"],"geometry":{"center":{"x":126.75431913709983,"y":35.45558793832251},"parts":[1],"style":null,"prjCoordSys":null,"id":96,"type":"POINT","partTopo":null,"points":[{"x":126.75431913709983,"y":35.45558793832251}]},"fieldValues":["96","0","[B@1ac1554","82","39","방장산","743.0","0.0","52790420","신림면"],"ID":96},{"stringID":null,"fieldNames":["SMID","SMUSERID","SMGEOMETRY","OBJ_ID","MNTN_ID","MNTN_NM","MNTN_HGHT","PHTGR_NO","EMNDN_CD","EMNDN_NM"],"geometry":{"center":{"x":128.25666733208251,"y":36.9847891157796},"parts":[1],"style":null,"prjCoordSys":null,"id":97,"type":"POINT","partTopo":null,"points":[{"x":128.25666733208251,"y":36.9847891157796}]},"fieldValues":["97","0","[B@4a4a7e6e","92","13","금수산","1016.0","0.0","43150330","수산면"],"ID":97},{"stringID":null,"fieldNames":["SMID","SMUSERID","SMGEOMETRY","OBJ_ID","MNTN_ID","MNTN_NM","MNTN_HGHT","PHTGR_NO","EMNDN_CD","EMNDN_NM"],"geometry":{"center":{"x":129.00469941926093,"y":37.426410079904535},"parts":[1],"style":null,"prjCoordSys":null,"id":98,"type":"POINT","partTopo":null,"points":[{"x":129.00469941926093,"y":37.426410079904535}]},"fieldValues":["98","0","[B@2038369","2","29","두타산","1353.0","0.0","51170124","삼화동"],"ID":98},{"stringID":null,"fieldNames":["SMID","SMUSERID","SMGEOMETRY","OBJ_ID","MNTN_ID","MNTN_NM","MNTN_HGHT","PHTGR_NO","EMNDN_CD","EMNDN_NM"],"geometry":{"center":{"x":126.70404406988784,"y":34.766549898885955},"parts":[1],"style":null,"prjCoordSys":null,"id":99,"type":"POINT","partTopo":null,"points":[{"x":126.70404406988784,"y":34.766549898885955}]},"fieldValues":["99","0","[B@5b28f067","70","67","월출산","809.0","0.0","46830250","영암읍"],"ID":99},{"stringID":null,"fieldNames":["SMID","SMUSERID","SMGEOMETRY","OBJ_ID","MNTN_ID","MNTN_NM","MNTN_HGHT","PHTGR_NO","EMNDN_CD","EMNDN_NM"],"geometry":{"center":{"x":128.4843601692895,"y":36.957366337568324},"parts":[1],"style":null,"prjCoordSys":null,"id":100,"type":"POINT","partTopo":null,"points":[{"x":128.4843601692895,"y":36.957366337568324}]},"fieldValues":["100","0","[B@3acf48e3","94","54","소백산","1439.0","0.0","43800320","가곡면"],"ID":100}],"featureUriList":[],"totalCount":100,"featureCount":100}